setup.cfg
setup.py
EinsteinVision/EinsteinVision.py
EinsteinVision/__init__.py
EinsteinVision.egg-info/PKG-INFO
EinsteinVision.egg-info/SOURCES.txt
EinsteinVision.egg-info/dependency_links.txt
EinsteinVision.egg-info/requires.txt
EinsteinVision.egg-info/top_level.txt