Metadata-Version: 1.1
Name: EinsteinVision
Version: 0.7
Summary: Wrapper for Salesforce's Einstein Predictive Vision API
Home-page: https://github.com/feliperyan/EinsteinVisionPython
Author: Felipe Ryan
Author-email: fryan@salesforce.com
License: UNKNOWN
Keywords: api einstein predictive vision metamind salesforce
Platform: UNKNOWN
Classifier: Development Status :: 3 - Alpha
Classifier: Intended Audience :: Developers
Classifier: Topic :: Software Development
Classifier: License :: OSI Approved :: BSD License
Classifier: Programming Language :: Python :: 3
Classifier: Programming Language :: Python :: 3.4
Classifier: Programming Language :: Python :: 3.5
Classifier: Programming Language :: Python :: 3.6
Classifier: Programming Language :: Python :: 3.7
